rscylladb/__init__.py
rscylladb/bulk.py
rscylladb/cdc.py
rscylladb/connect.py
rscylladb/logger.py
rscylladb/schema.py
rscylladb-1.0.5.dist-info/METADATA
rscylladb-1.0.5.dist-info/WHEEL
rscylladb-1.0.5.dist-info/top_level.txt
rscylladb-1.0.5.dist-info/RECORD
