Metadata-Version: 2.1
Name: rscylladb
Version: 1.0.5
Summary: Bulk records add into Cassandra or ScyllaDB.
Home-page: UNKNOWN
Author: Reeya Patel and Meet Rathod
Author-email: 
License: UNKNOWN
Platform: UNKNOWN
Requires-Dist: cassandra-driver (==3.29.0)
Requires-Dist: numpy
Requires-Dist: pandas
Requires-Dist: pyarrow
